asr/__init__.py
asr/__main__.py
asr/asr.py
asr/bader.py
asr/bandstructure.py
asr/berry.py
asr/borncharges.py
asr/bse.py
asr/chc.py
asr/convex_hull.py
asr/defectformation.py
asr/deformationpotentials.py
asr/dimensionality.py
asr/dos.py
asr/emasses.py
asr/exchange.py
asr/fere.py
asr/fermisurface.py
asr/formalpolarization.py
asr/gs.py
asr/gw.py
asr/hse.py
asr/infraredpolarizability.py
asr/magnetic_anisotropy.py
asr/magstate.py
asr/pdos.py
asr/phonons.py
asr/phonopy.py
asr/piezoelectrictensor.py
asr/plasmafrequency.py
asr/polarizability.py
asr/projected_bandstructure.py
asr/push.py
asr/raman.py
asr/relax.py
asr/setinfo.py
asr/stiffness.py
asr/structureinfo.py
asr/workflow.py
asr/calculators/__init__.py
asr/core/__init__.py
asr/core/cli.py
asr/core/command.py
asr/core/fix_old_files.py
asr/core/material.py
asr/core/results.py
asr/core/types.py
asr/core/utils.py
asr/database/__init__.py
asr/database/app.py
asr/database/browser.py
asr/database/check.py
asr/database/clonetree.py
asr/database/duplicates.py
asr/database/fromtree.py
asr/database/key_descriptions.py
asr/database/material_fingerprint.py
asr/database/merge.py
asr/database/rmsd.py
asr/database/totree.py
asr/database/templates/__init__.py
asr/database/templates/data.html
asr/database/templates/js.html
asr/database/templates/layout.html
asr/database/templates/projects.html
asr/database/templates/row.html
asr/database/templates/search.html
asr/database/templates/style.html
asr/database/templates/table.html
asr/setup/__init__.py
asr/setup/decorate.py
asr/setup/defects.py
asr/setup/displacements.py
asr/setup/magnetize.py
asr/setup/materials.py
asr/setup/params.py
asr/setup/scanparams.py
asr/setup/strains.py
asr/setup/substitution.dat
asr/setup/symmetrize.py
asr/setup/testsystems.json
asr/test/__init__.py
asr/test/conftest.py
asr/test/fixtures.py
asr/test/materials.py
asr/test/test_bandstructure.py
asr/test/test_berry.py
asr/test/test_borncharges.py
asr/test/test_bse.py
asr/test/test_cli.py
asr/test/test_convex_hull.py
asr-0.4.1.dist-info/AUTHORS.rst
asr-0.4.1.dist-info/LICENSE
asr-0.4.1.dist-info/METADATA
asr-0.4.1.dist-info/WHEEL
asr-0.4.1.dist-info/entry_points.txt
asr-0.4.1.dist-info/top_level.txt
asr-0.4.1.dist-info/RECORD
