Metadata-Version: 1.2
Name: asr
Version: 0.4.1
Summary: ASE recipes for calculating material properties
Home-page: https://gitlab.com/mortengjerding/asr
Author: Morten Niklas Gjerding
Author-email: mortengjerding@gmail.com
License: GNU General Public License v3
Keywords: asr
Platform: UNKNOWN
Classifier: Development Status :: 2 - Pre-Alpha
Classifier: Intended Audience :: Developers
Classifier: License :: OSI Approved :: GNU General Public License v3 (GPLv3)
Classifier: Natural Language :: English
Classifier: Programming Language :: Python :: 3
Classifier: Programming Language :: Python :: 3.5
Classifier: Programming Language :: Python :: 3.6
Classifier: Programming Language :: Python :: 3.7
Classifier: Programming Language :: Python :: 3.8
Requires-Python: >=3.5
